textract_hocr/__init__.py
textract_hocr/cli.py
textract_hocr/converter.py
textract_hocr-0.1.3.dist-info/licenses/LICENSE
textract_hocr-0.1.3.dist-info/METADATA
textract_hocr-0.1.3.dist-info/WHEEL
textract_hocr-0.1.3.dist-info/entry_points.txt
textract_hocr-0.1.3.dist-info/top_level.txt
textract_hocr-0.1.3.dist-info/RECORD
