Metadata-Version: 2.4
Name: textract-hocr
Version: 0.1.3
Summary: Convert AWS Textract JSON output to hOCR format
Author: BlueBox WorldWide, textract-hocr contributors
License: MIT
Project-URL: Homepage, https://github.com/BlueBox-WorldWide/textract-hocr
Project-URL: Bug Reports, https://github.com/BlueBox-WorldWide/textract-hocr/issues
Project-URL: Source, https://github.com/BlueBox-WorldWide/textract-hocr
Project-URL: Original AWS Samples, https://github.com/aws-samples/amazon-textract-hocr-output
Keywords: aws,textract,hocr,ocr,conversion
Classifier: Development Status :: 4 - Beta
Classifier: Intended Audience :: Developers
Classifier: License :: OSI Approved :: MIT License
Classifier: Programming Language :: Python :: 3
Classifier: Programming Language :: Python :: 3.8
Classifier: Programming Language :: Python :: 3.9
Classifier: Programming Language :: Python :: 3.10
Classifier: Programming Language :: Python :: 3.11
Classifier: Programming Language :: Python :: 3.12
Classifier: Programming Language :: Python :: 3.13
Classifier: Programming Language :: Python :: 3.14
Classifier: Programming Language :: Python :: 3.15
Classifier: Topic :: Text Processing :: Markup :: HTML
Classifier: Topic :: Scientific/Engineering :: Image Recognition
Requires-Python: >=3.8
License-File: LICENSE
Requires-Dist: yattag>=1.14.0
Requires-Dist: Pillow>=9.0.0
Provides-Extra: dev
Requires-Dist: pytest>=7.0.0; extra == "dev"
Requires-Dist: black>=22.0.0; extra == "dev"
Requires-Dist: flake8>=4.0.0; extra == "dev"
Dynamic: license-file
